.gitignore
LICENSE.txt
MANIFEST.in
setup.py
stdeb.cfg
motmot/__init__.py
motmot.realtime_image_analysis_ipp.egg-info/PKG-INFO
motmot.realtime_image_analysis_ipp.egg-info/SOURCES.txt
motmot.realtime_image_analysis_ipp.egg-info/dependency_links.txt
motmot.realtime_image_analysis_ipp.egg-info/namespace_packages.txt
motmot.realtime_image_analysis_ipp.egg-info/top_level.txt
motmot/realtime_image_analysis/__init__.py
motmot/realtime_image_analysis/slow.py
motmot/realtime_image_analysis/tests.py
src/ads_wrap_system.h
src/c_fit_params.cpp
src/c_fit_params.h
src/c_lib.pxd
src/c_python.pxd
src/c_time_time.c
src/c_time_time.h
src/eigen.c
src/eigen.h
src/fi_ipp.h
src/fic.c
src/fic.h
src/fic.pxd
src/fit_params.pxd
src/ipp.pxd
src/motmot.FastImage.FastImage.pxd
src/motmot_ria_macros.h
src/opencv.pxd
src/realtime_image_analysis.cpp
src/realtime_image_analysis.pyx